lunaticpypi/__init__.py
lunaticpypi/lunaticpypi.py
lunaticpypi-0.0.1.dist-info/LICENSE
lunaticpypi-0.0.1.dist-info/METADATA
lunaticpypi-0.0.1.dist-info/WHEEL
lunaticpypi-0.0.1.dist-info/top_level.txt
lunaticpypi-0.0.1.dist-info/RECORD
