Metadata-Version: 2.1
Name: lunaticpypi
Version: 0.0.1
Summary: This is a demo:)
Home-page: 
Author: Lunatic
Author-email: goodlunatic0@gmail.com
Classifier: Programming Language :: Python :: 3
Classifier: License :: OSI Approved :: MIT License
Classifier: Operating System :: OS Independent
License-File: LICENSE
